spliceai_pytorch/__init__.py
spliceai_pytorch/data.py
spliceai_pytorch/spliceai_pytorch.py
spliceai_pytorch/train.py
spliceai_pytorch-0.0.4.dist-info/METADATA
spliceai_pytorch-0.0.4.dist-info/WHEEL
spliceai_pytorch-0.0.4.dist-info/top_level.txt
spliceai_pytorch-0.0.4.dist-info/RECORD
